main_cookiestream.py
cookiestream/__init__.py
cookiestream/configs/__init__.py
cookiestream/configs/base_config.py
cookiestream/src/__init__.py
cookiestream/src/clone_template.py
cookiestream/src/make_rename.py
cookiestream/src/modify_yaml_content.py
cookiestream/src/stream.py
cookiestream/utils/__init__.py
cookiestream/utils/util.py
cookiestream-0.0.1.7.dist-info/LICENCE
cookiestream-0.0.1.7.dist-info/METADATA
cookiestream-0.0.1.7.dist-info/WHEEL
cookiestream-0.0.1.7.dist-info/entry_points.txt
cookiestream-0.0.1.7.dist-info/top_level.txt
cookiestream-0.0.1.7.dist-info/RECORD
