Metadata-Version: 2.1
Name: cookiestream
Version: 0.0.1.7
Summary: Generate template based on template_vierge project
Home-page: https://github.com/Proxia-ai/cookiestream
Author: BEN OTHMANE Zied
Author-email: ziedici@gmail.com
License: BSD
Project-URL: Bug Tracker, https://github.com/Proxia-ai/cookiestream/issues
Keywords: Python pypi template,python
Classifier: Programming Language :: Python :: 3
Classifier: License :: OSI Approved :: MIT License
Classifier: Operating System :: OS Independent
Classifier: Topic :: Software Development :: Build Tools
Classifier: Development Status :: 3 - Alpha
Classifier: Intended Audience :: Developers
Classifier: Programming Language :: Python :: 3.7
Requires-Python: >=3.7
License-File: LICENCE
Requires-Dist: PyYAML
Requires-Dist: streamlit
Requires-Dist: ruamel.yaml
